{
  "name" : "MaestroWorkflowExecutorTest",
  "key" : "com.netflix.conductor.core.execution.MaestroWorkflowExecutorTest",
  "type" : "class",
  "displayedType" : null,
  "hasTypeVariable" : false,
  "position" : {
    "startLine" : 59,
    "startColumn" : 8,
    "endLine" : 59,
    "endColumn" : 13
  },
  "modifiers" : [ "PUBLIC" ],
  "fields" : {
    "com.netflix.conductor.core.execution.MaestroWorkflowExecutorTest/memberField/metadataDAO" : {
      "name" : "metadataDAO",
      "key" : "com.netflix.conductor.core.execution.MaestroWorkflowExecutorTest/memberField/metadataDAO",
      "type" : "com.netflix.conductor.core.execution.com.netflix.conductor.dao.MetadataDAO",
      "displayedType" : "MetadataDAO",
      "hasTypeVariable" : false,
      "position" : {
        "startLine" : 61,
        "startColumn" : 21,
        "endLine" : 61,
        "endColumn" : 32
      },
      "modifiers" : [ ],
      "ignore" : false,
      "memberFieldKey" : null,
      "classOrInterfaceKey" : "com.netflix.conductor.core.execution.MaestroWorkflowExecutorTest"
    },
    "com.netflix.conductor.core.execution.MaestroWorkflowExecutorTest/memberField/metadataMapperService" : {
      "name" : "metadataMapperService",
      "key" : "com.netflix.conductor.core.execution.MaestroWorkflowExecutorTest/memberField/metadataMapperService",
      "type" : "com.netflix.conductor.core.execution.com.netflix.conductor.core.metadata.MetadataMapperService",
      "displayedType" : "MetadataMapperService",
      "hasTypeVariable" : false,
      "position" : {
        "startLine" : 63,
        "startColumn" : 31,
        "endLine" : 63,
        "endColumn" : 52
      },
      "modifiers" : [ ],
      "ignore" : false,
      "memberFieldKey" : null,
      "classOrInterfaceKey" : "com.netflix.conductor.core.execution.MaestroWorkflowExecutorTest"
    },
    "com.netflix.conductor.core.execution.MaestroWorkflowExecutorTest/memberField/workflowStatusListener" : {
      "name" : "workflowStatusListener",
      "key" : "com.netflix.conductor.core.execution.MaestroWorkflowExecutorTest/memberField/workflowStatusListener",
      "type" : "com.netflix.conductor.core.execution.WorkflowStatusListener",
      "displayedType" : "WorkflowStatusListener",
      "hasTypeVariable" : false,
      "position" : {
        "startLine" : 64,
        "startColumn" : 32,
        "endLine" : 64,
        "endColumn" : 54
      },
      "modifiers" : [ ],
      "ignore" : false,
      "memberFieldKey" : null,
      "classOrInterfaceKey" : "com.netflix.conductor.core.execution.MaestroWorkflowExecutorTest"
    },
    "com.netflix.conductor.core.execution.MaestroWorkflowExecutorTest/memberField/callbackPolicy" : {
      "name" : "callbackPolicy",
      "key" : "com.netflix.conductor.core.execution.MaestroWorkflowExecutorTest/memberField/callbackPolicy",
      "type" : "com.netflix.conductor.core.execution.com.netflix.maestro.engine.execution.StepRuntimeCallbackDelayPolicy",
      "displayedType" : "StepRuntimeCallbackDelayPolicy",
      "hasTypeVariable" : false,
      "position" : {
        "startLine" : 69,
        "startColumn" : 40,
        "endLine" : 69,
        "endColumn" : 54
      },
      "modifiers" : [ ],
      "ignore" : false,
      "memberFieldKey" : null,
      "classOrInterfaceKey" : "com.netflix.conductor.core.execution.MaestroWorkflowExecutorTest"
    },
    "com.netflix.conductor.core.execution.MaestroWorkflowExecutorTest/memberField/executionLockService" : {
      "name" : "executionLockService",
      "key" : "com.netflix.conductor.core.execution.MaestroWorkflowExecutorTest/memberField/executionLockService",
      "type" : "com.netflix.conductor.core.execution.com.netflix.conductor.service.ExecutionLockService",
      "displayedType" : "ExecutionLockService",
      "hasTypeVariable" : false,
      "position" : {
        "startLine" : 67,
        "startColumn" : 30,
        "endLine" : 67,
        "endColumn" : 50
      },
      "modifiers" : [ ],
      "ignore" : false,
      "memberFieldKey" : null,
      "classOrInterfaceKey" : "com.netflix.conductor.core.execution.MaestroWorkflowExecutorTest"
    },
    "com.netflix.conductor.core.execution.MaestroWorkflowExecutorTest/memberField/parametersUtils" : {
      "name" : "parametersUtils",
      "key" : "com.netflix.conductor.core.execution.MaestroWorkflowExecutorTest/memberField/parametersUtils",
      "type" : "com.netflix.conductor.core.execution.ParametersUtils",
      "displayedType" : "ParametersUtils",
      "hasTypeVariable" : false,
      "position" : {
        "startLine" : 68,
        "startColumn" : 25,
        "endLine" : 68,
        "endColumn" : 40
      },
      "modifiers" : [ ],
      "ignore" : false,
      "memberFieldKey" : null,
      "classOrInterfaceKey" : "com.netflix.conductor.core.execution.MaestroWorkflowExecutorTest"
    },
    "com.netflix.conductor.core.execution.MaestroWorkflowExecutorTest/memberField/deciderService" : {
      "name" : "deciderService",
      "key" : "com.netflix.conductor.core.execution.MaestroWorkflowExecutorTest/memberField/deciderService",
      "type" : "com.netflix.conductor.core.execution.DeciderService",
      "displayedType" : "DeciderService",
      "hasTypeVariable" : false,
      "position" : {
        "startLine" : 60,
        "startColumn" : 24,
        "endLine" : 60,
        "endColumn" : 38
      },
      "modifiers" : [ ],
      "ignore" : false,
      "memberFieldKey" : null,
      "classOrInterfaceKey" : "com.netflix.conductor.core.execution.MaestroWorkflowExecutorTest"
    },
    "com.netflix.conductor.core.execution.MaestroWorkflowExecutorTest/memberField/task2" : {
      "name" : "task2",
      "key" : "com.netflix.conductor.core.execution.MaestroWorkflowExecutorTest/memberField/task2",
      "type" : "com.netflix.conductor.core.execution.MaestroWorkflowExecutorTest$TestTask",
      "displayedType" : "TestTask",
      "hasTypeVariable" : false,
      "position" : {
        "startLine" : 74,
        "startColumn" : 20,
        "endLine" : 74,
        "endColumn" : 25
      },
      "modifiers" : [ "PRIVATE" ],
      "ignore" : false,
      "memberFieldKey" : null,
      "classOrInterfaceKey" : "com.netflix.conductor.core.execution.MaestroWorkflowExecutorTest"
    },
    "com.netflix.conductor.core.execution.MaestroWorkflowExecutorTest/memberField/maestroWorkflowExecutor" : {
      "name" : "maestroWorkflowExecutor",
      "key" : "com.netflix.conductor.core.execution.MaestroWorkflowExecutorTest/memberField/maestroWorkflowExecutor",
      "type" : "com.netflix.conductor.core.execution.MaestroWorkflowExecutor",
      "displayedType" : "MaestroWorkflowExecutor",
      "hasTypeVariable" : false,
      "position" : {
        "startLine" : 71,
        "startColumn" : 35,
        "endLine" : 71,
        "endColumn" : 58
      },
      "modifiers" : [ "PRIVATE" ],
      "ignore" : false,
      "memberFieldKey" : null,
      "classOrInterfaceKey" : "com.netflix.conductor.core.execution.MaestroWorkflowExecutorTest"
    },
    "com.netflix.conductor.core.execution.MaestroWorkflowExecutorTest/memberField/task1" : {
      "name" : "task1",
      "key" : "com.netflix.conductor.core.execution.MaestroWorkflowExecutorTest/memberField/task1",
      "type" : "com.netflix.conductor.core.execution.MaestroWorkflowExecutorTest$TestTask",
      "displayedType" : "TestTask",
      "hasTypeVariable" : false,
      "position" : {
        "startLine" : 73,
        "startColumn" : 20,
        "endLine" : 73,
        "endColumn" : 25
      },
      "modifiers" : [ "PRIVATE" ],
      "ignore" : false,
      "memberFieldKey" : null,
      "classOrInterfaceKey" : "com.netflix.conductor.core.execution.MaestroWorkflowExecutorTest"
    },
    "com.netflix.conductor.core.execution.MaestroWorkflowExecutorTest/memberField/executionDAOFacade" : {
      "name" : "executionDAOFacade",
      "key" : "com.netflix.conductor.core.execution.MaestroWorkflowExecutorTest/memberField/executionDAOFacade",
      "type" : "com.netflix.conductor.core.execution.com.netflix.conductor.core.orchestration.ExecutionDAOFacade",
      "displayedType" : "ExecutionDAOFacade",
      "hasTypeVariable" : false,
      "position" : {
        "startLine" : 65,
        "startColumn" : 28,
        "endLine" : 65,
        "endColumn" : 46
      },
      "modifiers" : [ ],
      "ignore" : false,
      "memberFieldKey" : null,
      "classOrInterfaceKey" : "com.netflix.conductor.core.execution.MaestroWorkflowExecutorTest"
    },
    "com.netflix.conductor.core.execution.MaestroWorkflowExecutorTest/memberField/props" : {
      "name" : "props",
      "key" : "com.netflix.conductor.core.execution.MaestroWorkflowExecutorTest/memberField/props",
      "type" : "com.netflix.conductor.core.execution.com.netflix.maestro.engine.properties.MaestroConductorProperties",
      "displayedType" : "MaestroConductorProperties",
      "hasTypeVariable" : false,
      "position" : {
        "startLine" : 66,
        "startColumn" : 36,
        "endLine" : 66,
        "endColumn" : 41
      },
      "modifiers" : [ ],
      "ignore" : false,
      "memberFieldKey" : null,
      "classOrInterfaceKey" : "com.netflix.conductor.core.execution.MaestroWorkflowExecutorTest"
    },
    "com.netflix.conductor.core.execution.MaestroWorkflowExecutorTest/memberField/workflow" : {
      "name" : "workflow",
      "key" : "com.netflix.conductor.core.execution.MaestroWorkflowExecutorTest/memberField/workflow",
      "type" : "com.netflix.conductor.core.execution.com.netflix.conductor.common.run.Workflow",
      "displayedType" : "Workflow",
      "hasTypeVariable" : false,
      "position" : {
        "startLine" : 72,
        "startColumn" : 20,
        "endLine" : 72,
        "endColumn" : 28
      },
      "modifiers" : [ "PRIVATE" ],
      "ignore" : false,
      "memberFieldKey" : null,
      "classOrInterfaceKey" : "com.netflix.conductor.core.execution.MaestroWorkflowExecutorTest"
    },
    "com.netflix.conductor.core.execution.MaestroWorkflowExecutorTest/memberField/queueDAO" : {
      "name" : "queueDAO",
      "key" : "com.netflix.conductor.core.execution.MaestroWorkflowExecutorTest/memberField/queueDAO",
      "type" : "com.netflix.conductor.core.execution.com.netflix.conductor.dao.QueueDAO",
      "displayedType" : "QueueDAO",
      "hasTypeVariable" : false,
      "position" : {
        "startLine" : 62,
        "startColumn" : 18,
        "endLine" : 62,
        "endColumn" : 26
      },
      "modifiers" : [ ],
      "ignore" : false,
      "memberFieldKey" : null,
      "classOrInterfaceKey" : "com.netflix.conductor.core.execution.MaestroWorkflowExecutorTest"
    }
  },
  "methods" : {
    "com.netflix.conductor.core.execution.MaestroWorkflowExecutorTest/method/testExecuteSystemTaskWithoutUpdatingPollingCount()" : {
      "name" : "testExecuteSystemTaskWithoutUpdatingPollingCount",
      "key" : "com.netflix.conductor.core.execution.MaestroWorkflowExecutorTest/method/testExecuteSystemTaskWithoutUpdatingPollingCount()",
      "type" : "void",
      "displayedType" : "void",
      "hasTypeVariable" : false,
      "position" : {
        "startLine" : 363,
        "startColumn" : 15,
        "endLine" : 363,
        "endColumn" : 63
      },
      "modifiers" : [ "PUBLIC" ],
      "overrideAnnotation" : false,
      "returnType" : null,
      "parameters" : [ ],
      "classOrInterfaceKey" : "com.netflix.conductor.core.execution.MaestroWorkflowExecutorTest"
    },
    "com.netflix.conductor.core.execution.MaestroWorkflowExecutorTest/method/testResetOffset()" : {
      "name" : "testResetOffset",
      "key" : "com.netflix.conductor.core.execution.MaestroWorkflowExecutorTest/method/testResetOffset()",
      "type" : "void",
      "displayedType" : "void",
      "hasTypeVariable" : false,
      "position" : {
        "startLine" : 454,
        "startColumn" : 15,
        "endLine" : 454,
        "endColumn" : 30
      },
      "modifiers" : [ "PUBLIC" ],
      "overrideAnnotation" : false,
      "returnType" : null,
      "parameters" : [ ],
      "classOrInterfaceKey" : "com.netflix.conductor.core.execution.MaestroWorkflowExecutorTest"
    },
    "com.netflix.conductor.core.execution.MaestroWorkflowExecutorTest/method/testCancelNonTerminalTasksFailed()" : {
      "name" : "testCancelNonTerminalTasksFailed",
      "key" : "com.netflix.conductor.core.execution.MaestroWorkflowExecutorTest/method/testCancelNonTerminalTasksFailed()",
      "type" : "void",
      "displayedType" : "void",
      "hasTypeVariable" : false,
      "position" : {
        "startLine" : 291,
        "startColumn" : 15,
        "endLine" : 291,
        "endColumn" : 47
      },
      "modifiers" : [ "PUBLIC" ],
      "overrideAnnotation" : false,
      "returnType" : null,
      "parameters" : [ ],
      "classOrInterfaceKey" : "com.netflix.conductor.core.execution.MaestroWorkflowExecutorTest"
    },
    "com.netflix.conductor.core.execution.MaestroWorkflowExecutorTest/method/testConfigureCallBack()" : {
      "name" : "testConfigureCallBack",
      "key" : "com.netflix.conductor.core.execution.MaestroWorkflowExecutorTest/method/testConfigureCallBack()",
      "type" : "void",
      "displayedType" : "void",
      "hasTypeVariable" : false,
      "position" : {
        "startLine" : 133,
        "startColumn" : 15,
        "endLine" : 133,
        "endColumn" : 36
      },
      "modifiers" : [ "PUBLIC" ],
      "overrideAnnotation" : false,
      "returnType" : null,
      "parameters" : [ ],
      "classOrInterfaceKey" : "com.netflix.conductor.core.execution.MaestroWorkflowExecutorTest"
    },
    "com.netflix.conductor.core.execution.MaestroWorkflowExecutorTest/method/testExecuteSystemTaskThrowUnexpectedException()" : {
      "name" : "testExecuteSystemTaskThrowUnexpectedException",
      "key" : "com.netflix.conductor.core.execution.MaestroWorkflowExecutorTest/method/testExecuteSystemTaskThrowUnexpectedException()",
      "type" : "void",
      "displayedType" : "void",
      "hasTypeVariable" : false,
      "position" : {
        "startLine" : 423,
        "startColumn" : 15,
        "endLine" : 423,
        "endColumn" : 60
      },
      "modifiers" : [ "PUBLIC" ],
      "overrideAnnotation" : false,
      "returnType" : null,
      "parameters" : [ ],
      "classOrInterfaceKey" : "com.netflix.conductor.core.execution.MaestroWorkflowExecutorTest"
    },
    "com.netflix.conductor.core.execution.MaestroWorkflowExecutorTest/method/testResetOffsetNotFound()" : {
      "name" : "testResetOffsetNotFound",
      "key" : "com.netflix.conductor.core.execution.MaestroWorkflowExecutorTest/method/testResetOffsetNotFound()",
      "type" : "void",
      "displayedType" : "void",
      "hasTypeVariable" : false,
      "position" : {
        "startLine" : 498,
        "startColumn" : 15,
        "endLine" : 498,
        "endColumn" : 38
      },
      "modifiers" : [ "PUBLIC" ],
      "overrideAnnotation" : false,
      "returnType" : null,
      "parameters" : [ ],
      "classOrInterfaceKey" : "com.netflix.conductor.core.execution.MaestroWorkflowExecutorTest"
    },
    "com.netflix.conductor.core.execution.MaestroWorkflowExecutorTest/method/testCancelNonTerminalTasks()" : {
      "name" : "testCancelNonTerminalTasks",
      "key" : "com.netflix.conductor.core.execution.MaestroWorkflowExecutorTest/method/testCancelNonTerminalTasks()",
      "type" : "void",
      "displayedType" : "void",
      "hasTypeVariable" : false,
      "position" : {
        "startLine" : 251,
        "startColumn" : 15,
        "endLine" : 251,
        "endColumn" : 41
      },
      "modifiers" : [ "PUBLIC" ],
      "overrideAnnotation" : false,
      "returnType" : null,
      "parameters" : [ ],
      "classOrInterfaceKey" : "com.netflix.conductor.core.execution.MaestroWorkflowExecutorTest"
    },
    "com.netflix.conductor.core.execution.MaestroWorkflowExecutorTest/method/testExecuteSystemTaskThrowExceptionDuringConfigureCallbackInterval()" : {
      "name" : "testExecuteSystemTaskThrowExceptionDuringConfigureCallbackInterval",
      "key" : "com.netflix.conductor.core.execution.MaestroWorkflowExecutorTest/method/testExecuteSystemTaskThrowExceptionDuringConfigureCallbackInterval()",
      "type" : "void",
      "displayedType" : "void",
      "hasTypeVariable" : false,
      "position" : {
        "startLine" : 541,
        "startColumn" : 15,
        "endLine" : 541,
        "endColumn" : 81
      },
      "modifiers" : [ "PUBLIC" ],
      "overrideAnnotation" : false,
      "returnType" : null,
      "parameters" : [ ],
      "classOrInterfaceKey" : "com.netflix.conductor.core.execution.MaestroWorkflowExecutorTest"
    },
    "com.netflix.conductor.core.execution.MaestroWorkflowExecutorTest/method/testExecuteSystemTaskPersistStartTime()" : {
      "name" : "testExecuteSystemTaskPersistStartTime",
      "key" : "com.netflix.conductor.core.execution.MaestroWorkflowExecutorTest/method/testExecuteSystemTaskPersistStartTime()",
      "type" : "void",
      "displayedType" : "void",
      "hasTypeVariable" : false,
      "position" : {
        "startLine" : 392,
        "startColumn" : 15,
        "endLine" : 392,
        "endColumn" : 52
      },
      "modifiers" : [ "PUBLIC" ],
      "overrideAnnotation" : false,
      "returnType" : null,
      "parameters" : [ ],
      "classOrInterfaceKey" : "com.netflix.conductor.core.execution.MaestroWorkflowExecutorTest"
    },
    "com.netflix.conductor.core.execution.MaestroWorkflowExecutorTest/method/testFinalizedFailure()" : {
      "name" : "testFinalizedFailure",
      "key" : "com.netflix.conductor.core.execution.MaestroWorkflowExecutorTest/method/testFinalizedFailure()",
      "type" : "void",
      "displayedType" : "void",
      "hasTypeVariable" : false,
      "position" : {
        "startLine" : 328,
        "startColumn" : 15,
        "endLine" : 328,
        "endColumn" : 35
      },
      "modifiers" : [ "PUBLIC" ],
      "overrideAnnotation" : false,
      "returnType" : null,
      "parameters" : [ ],
      "classOrInterfaceKey" : "com.netflix.conductor.core.execution.MaestroWorkflowExecutorTest"
    },
    "com.netflix.conductor.core.execution.MaestroWorkflowExecutorTest/method/testConfigureCallBackForRunningForeachStepWithFirstPolling()" : {
      "name" : "testConfigureCallBackForRunningForeachStepWithFirstPolling",
      "key" : "com.netflix.conductor.core.execution.MaestroWorkflowExecutorTest/method/testConfigureCallBackForRunningForeachStepWithFirstPolling()",
      "type" : "void",
      "displayedType" : "void",
      "hasTypeVariable" : false,
      "position" : {
        "startLine" : 162,
        "startColumn" : 15,
        "endLine" : 162,
        "endColumn" : 73
      },
      "modifiers" : [ "PUBLIC" ],
      "overrideAnnotation" : false,
      "returnType" : null,
      "parameters" : [ ],
      "classOrInterfaceKey" : "com.netflix.conductor.core.execution.MaestroWorkflowExecutorTest"
    },
    "com.netflix.conductor.core.execution.MaestroWorkflowExecutorTest/method/testConfigureCallBackForStartTaskWithFirstPolling()" : {
      "name" : "testConfigureCallBackForStartTaskWithFirstPolling",
      "key" : "com.netflix.conductor.core.execution.MaestroWorkflowExecutorTest/method/testConfigureCallBackForStartTaskWithFirstPolling()",
      "type" : "void",
      "displayedType" : "void",
      "hasTypeVariable" : false,
      "position" : {
        "startLine" : 226,
        "startColumn" : 15,
        "endLine" : 226,
        "endColumn" : 64
      },
      "modifiers" : [ "PUBLIC" ],
      "overrideAnnotation" : false,
      "returnType" : null,
      "parameters" : [ ],
      "classOrInterfaceKey" : "com.netflix.conductor.core.execution.MaestroWorkflowExecutorTest"
    },
    "com.netflix.conductor.core.execution.MaestroWorkflowExecutorTest/method/testConfigureCallBackForJustCreatedMaestroTaskWithFirstPolling()" : {
      "name" : "testConfigureCallBackForJustCreatedMaestroTaskWithFirstPolling",
      "key" : "com.netflix.conductor.core.execution.MaestroWorkflowExecutorTest/method/testConfigureCallBackForJustCreatedMaestroTaskWithFirstPolling()",
      "type" : "void",
      "displayedType" : "void",
      "hasTypeVariable" : false,
      "position" : {
        "startLine" : 194,
        "startColumn" : 15,
        "endLine" : 194,
        "endColumn" : 77
      },
      "modifiers" : [ "PUBLIC" ],
      "overrideAnnotation" : false,
      "returnType" : null,
      "parameters" : [ ],
      "classOrInterfaceKey" : "com.netflix.conductor.core.execution.MaestroWorkflowExecutorTest"
    },
    "com.netflix.conductor.core.execution.MaestroWorkflowExecutorTest/method/before()" : {
      "name" : "before",
      "key" : "com.netflix.conductor.core.execution.MaestroWorkflowExecutorTest/method/before()",
      "type" : "void",
      "displayedType" : "void",
      "hasTypeVariable" : false,
      "position" : {
        "startLine" : 77,
        "startColumn" : 15,
        "endLine" : 77,
        "endColumn" : 21
      },
      "modifiers" : [ "PUBLIC" ],
      "overrideAnnotation" : false,
      "returnType" : null,
      "parameters" : [ ],
      "classOrInterfaceKey" : "com.netflix.conductor.core.execution.MaestroWorkflowExecutorTest"
    }
  },
  "file_path" : "maestro-engine/src/test/java/com/netflix/conductor/core/execution/MaestroWorkflowExecutorTest.java",
  "imports" : [ ],
  "anonymous" : false,
  "auxclass" : false,
  "implements_" : [ ],
  "extends_" : [ "com.netflix.conductor.core.execution.com.netflix.maestro.engine.MaestroEngineBaseTest" ],
  "definedInClassOrInterfaceTypeKey" : null,
  "innerDefinedClasses" : {
    "com.netflix.conductor.core.execution.MaestroWorkflowExecutorTest.TestTask" : {
      "name" : "TestTask",
      "key" : "com.netflix.conductor.core.execution.MaestroWorkflowExecutorTest.TestTask",
      "type" : "class",
      "displayedType" : null,
      "hasTypeVariable" : false,
      "position" : {
        "startLine" : 109,
        "startColumn" : 18,
        "endLine" : 109,
        "endColumn" : 23
      },
      "modifiers" : [ "PRIVATE", "STATIC" ],
      "fields" : {
        "com.netflix.conductor.core.execution.MaestroWorkflowExecutorTest.TestTask/memberField/shouldThrow" : {
          "name" : "shouldThrow",
          "key" : "com.netflix.conductor.core.execution.MaestroWorkflowExecutorTest.TestTask/memberField/shouldThrow",
          "type" : "boolean",
          "displayedType" : "boolean",
          "hasTypeVariable" : false,
          "position" : {
            "startLine" : 110,
            "startColumn" : 29,
            "endLine" : 110,
            "endColumn" : 40
          },
          "modifiers" : [ "PRIVATE" ],
          "ignore" : false,
          "memberFieldKey" : null,
          "classOrInterfaceKey" : "com.netflix.conductor.core.execution.MaestroWorkflowExecutorTest.TestTask"
        }
      },
      "methods" : {
        "com.netflix.conductor.core.execution.MaestroWorkflowExecutorTest.TestTask/method/execute(com.netflix.conductor.core.execution.com.netflix.conductor.common.run.Workflow workflow, com.netflix.conductor.core.execution.com.netflix.conductor.common.metadata.tasks.Task task, com.netflix.conductor.core.execution.WorkflowExecutor executor)" : {
          "name" : "execute",
          "key" : "com.netflix.conductor.core.execution.MaestroWorkflowExecutorTest.TestTask/method/execute(com.netflix.conductor.core.execution.com.netflix.conductor.common.run.Workflow workflow, com.netflix.conductor.core.execution.com.netflix.conductor.common.metadata.tasks.Task task, com.netflix.conductor.core.execution.WorkflowExecutor executor)",
          "type" : "boolean",
          "displayedType" : "boolean",
          "hasTypeVariable" : false,
          "position" : {
            "startLine" : 117,
            "startColumn" : 20,
            "endLine" : 117,
            "endColumn" : 27
          },
          "modifiers" : [ "PUBLIC" ],
          "overrideAnnotation" : true,
          "returnType" : null,
          "parameters" : [ {
            "name" : "workflow",
            "key" : "com.netflix.conductor.core.execution.MaestroWorkflowExecutorTest.TestTask/method/execute(com.netflix.conductor.core.execution.com.netflix.conductor.common.run.Workflow workflow, com.netflix.conductor.core.execution.com.netflix.conductor.common.metadata.tasks.Task task, com.netflix.conductor.core.execution.WorkflowExecutor executor)/parameter/workflow",
            "type" : "com.netflix.conductor.core.execution.com.netflix.conductor.common.run.Workflow",
            "displayedType" : "Workflow",
            "hasTypeVariable" : false,
            "position" : {
              "startLine" : 117,
              "startColumn" : 37,
              "endLine" : 117,
              "endColumn" : 45
            },
            "modifiers" : [ ],
            "ignore" : false,
            "methodKey" : "com.netflix.conductor.core.execution.MaestroWorkflowExecutorTest.TestTask/method/execute(com.netflix.conductor.core.execution.com.netflix.conductor.common.run.Workflow workflow, com.netflix.conductor.core.execution.com.netflix.conductor.common.metadata.tasks.Task task, com.netflix.conductor.core.execution.WorkflowExecutor executor)"
          }, {
            "name" : "task",
            "key" : "com.netflix.conductor.core.execution.MaestroWorkflowExecutorTest.TestTask/method/execute(com.netflix.conductor.core.execution.com.netflix.conductor.common.run.Workflow workflow, com.netflix.conductor.core.execution.com.netflix.conductor.common.metadata.tasks.Task task, com.netflix.conductor.core.execution.WorkflowExecutor executor)/parameter/task",
            "type" : "com.netflix.conductor.core.execution.com.netflix.conductor.common.metadata.tasks.Task",
            "displayedType" : "Task",
            "hasTypeVariable" : false,
            "position" : {
              "startLine" : 117,
              "startColumn" : 52,
              "endLine" : 117,
              "endColumn" : 56
            },
            "modifiers" : [ ],
            "ignore" : false,
            "methodKey" : "com.netflix.conductor.core.execution.MaestroWorkflowExecutorTest.TestTask/method/execute(com.netflix.conductor.core.execution.com.netflix.conductor.common.run.Workflow workflow, com.netflix.conductor.core.execution.com.netflix.conductor.common.metadata.tasks.Task task, com.netflix.conductor.core.execution.WorkflowExecutor executor)"
          }, {
            "name" : "executor",
            "key" : "com.netflix.conductor.core.execution.MaestroWorkflowExecutorTest.TestTask/method/execute(com.netflix.conductor.core.execution.com.netflix.conductor.common.run.Workflow workflow, com.netflix.conductor.core.execution.com.netflix.conductor.common.metadata.tasks.Task task, com.netflix.conductor.core.execution.WorkflowExecutor executor)/parameter/executor",
            "type" : "com.netflix.conductor.core.execution.WorkflowExecutor",
            "displayedType" : "WorkflowExecutor",
            "hasTypeVariable" : false,
            "position" : {
              "startLine" : 117,
              "startColumn" : 75,
              "endLine" : 117,
              "endColumn" : 83
            },
            "modifiers" : [ ],
            "ignore" : false,
            "methodKey" : "com.netflix.conductor.core.execution.MaestroWorkflowExecutorTest.TestTask/method/execute(com.netflix.conductor.core.execution.com.netflix.conductor.common.run.Workflow workflow, com.netflix.conductor.core.execution.com.netflix.conductor.common.metadata.tasks.Task task, com.netflix.conductor.core.execution.WorkflowExecutor executor)"
          } ],
          "classOrInterfaceKey" : "com.netflix.conductor.core.execution.MaestroWorkflowExecutorTest.TestTask"
        },
        "com.netflix.conductor.core.execution.MaestroWorkflowExecutorTest.TestTask/method/cancel(com.netflix.conductor.core.execution.com.netflix.conductor.common.run.Workflow workflow, com.netflix.conductor.core.execution.com.netflix.conductor.common.metadata.tasks.Task task, com.netflix.conductor.core.execution.WorkflowExecutor executor)" : {
          "name" : "cancel",
          "key" : "com.netflix.conductor.core.execution.MaestroWorkflowExecutorTest.TestTask/method/cancel(com.netflix.conductor.core.execution.com.netflix.conductor.common.run.Workflow workflow, com.netflix.conductor.core.execution.com.netflix.conductor.common.metadata.tasks.Task task, com.netflix.conductor.core.execution.WorkflowExecutor executor)",
          "type" : "void",
          "displayedType" : "void",
          "hasTypeVariable" : false,
          "position" : {
            "startLine" : 125,
            "startColumn" : 17,
            "endLine" : 125,
            "endColumn" : 23
          },
          "modifiers" : [ "PUBLIC" ],
          "overrideAnnotation" : true,
          "returnType" : null,
          "parameters" : [ {
            "name" : "workflow",
            "key" : "com.netflix.conductor.core.execution.MaestroWorkflowExecutorTest.TestTask/method/cancel(com.netflix.conductor.core.execution.com.netflix.conductor.common.run.Workflow workflow, com.netflix.conductor.core.execution.com.netflix.conductor.common.metadata.tasks.Task task, com.netflix.conductor.core.execution.WorkflowExecutor executor)/parameter/workflow",
            "type" : "com.netflix.conductor.core.execution.com.netflix.conductor.common.run.Workflow",
            "displayedType" : "Workflow",
            "hasTypeVariable" : false,
            "position" : {
              "startLine" : 125,
              "startColumn" : 33,
              "endLine" : 125,
              "endColumn" : 41
            },
            "modifiers" : [ ],
            "ignore" : false,
            "methodKey" : "com.netflix.conductor.core.execution.MaestroWorkflowExecutorTest.TestTask/method/cancel(com.netflix.conductor.core.execution.com.netflix.conductor.common.run.Workflow workflow, com.netflix.conductor.core.execution.com.netflix.conductor.common.metadata.tasks.Task task, com.netflix.conductor.core.execution.WorkflowExecutor executor)"
          }, {
            "name" : "task",
            "key" : "com.netflix.conductor.core.execution.MaestroWorkflowExecutorTest.TestTask/method/cancel(com.netflix.conductor.core.execution.com.netflix.conductor.common.run.Workflow workflow, com.netflix.conductor.core.execution.com.netflix.conductor.common.metadata.tasks.Task task, com.netflix.conductor.core.execution.WorkflowExecutor executor)/parameter/task",
            "type" : "com.netflix.conductor.core.execution.com.netflix.conductor.common.metadata.tasks.Task",
            "displayedType" : "Task",
            "hasTypeVariable" : false,
            "position" : {
              "startLine" : 125,
              "startColumn" : 48,
              "endLine" : 125,
              "endColumn" : 52
            },
            "modifiers" : [ ],
            "ignore" : false,
            "methodKey" : "com.netflix.conductor.core.execution.MaestroWorkflowExecutorTest.TestTask/method/cancel(com.netflix.conductor.core.execution.com.netflix.conductor.common.run.Workflow workflow, com.netflix.conductor.core.execution.com.netflix.conductor.common.metadata.tasks.Task task, com.netflix.conductor.core.execution.WorkflowExecutor executor)"
          }, {
            "name" : "executor",
            "key" : "com.netflix.conductor.core.execution.MaestroWorkflowExecutorTest.TestTask/method/cancel(com.netflix.conductor.core.execution.com.netflix.conductor.common.run.Workflow workflow, com.netflix.conductor.core.execution.com.netflix.conductor.common.metadata.tasks.Task task, com.netflix.conductor.core.execution.WorkflowExecutor executor)/parameter/executor",
            "type" : "com.netflix.conductor.core.execution.WorkflowExecutor",
            "displayedType" : "WorkflowExecutor",
            "hasTypeVariable" : false,
            "position" : {
              "startLine" : 125,
              "startColumn" : 71,
              "endLine" : 125,
              "endColumn" : 79
            },
            "modifiers" : [ ],
            "ignore" : false,
            "methodKey" : "com.netflix.conductor.core.execution.MaestroWorkflowExecutorTest.TestTask/method/cancel(com.netflix.conductor.core.execution.com.netflix.conductor.common.run.Workflow workflow, com.netflix.conductor.core.execution.com.netflix.conductor.common.metadata.tasks.Task task, com.netflix.conductor.core.execution.WorkflowExecutor executor)"
          } ],
          "classOrInterfaceKey" : "com.netflix.conductor.core.execution.MaestroWorkflowExecutorTest.TestTask"
        }
      },
      "file_path" : "maestro-engine/src/test/java/com/netflix/conductor/core/execution/MaestroWorkflowExecutorTest.java",
      "imports" : [ ],
      "anonymous" : false,
      "auxclass" : false,
      "implements_" : [ ],
      "extends_" : [ "com.netflix.conductor.core.execution.com.netflix.conductor.core.execution.tasks.WorkflowSystemTask" ],
      "definedInClassOrInterfaceTypeKey" : "com.netflix.conductor.core.execution.MaestroWorkflowExecutorTest",
      "innerDefinedClasses" : { },
      "innerDefinedInterfaces" : { }
    }
  },
  "innerDefinedInterfaces" : { }
}